askuser/__init__.py
askuser/autocomplete.py
askuser/core.py
askuser/custom_validators.py
askuser/logic.py
askuser-0.2.3.dist-info/licenses/LICENSE
askuser-0.2.3.dist-info/METADATA
askuser-0.2.3.dist-info/WHEEL
askuser-0.2.3.dist-info/top_level.txt
askuser-0.2.3.dist-info/RECORD
