Metadata-Version: 2.4
Name: askuser
Version: 0.2.3
Summary: Smart and robust CLI input: validated prompts, menu-driven selections, default value support, and smart autocompletion.
Author-email: "Kanad Rishiraj (RoamingSaint)" <roamingsaint27@gmail.com>
License: MIT
Requires-Python: >=3.7
License-File: LICENSE
Requires-Dist: colorfulPyPrint~=0.1
Requires-Dist: datetimeops~=1.0
Requires-Dist: prompt_toolkit~=3.0
Requires-Dist: pycountry~=24.6
Requires-Dist: string-list~=0.1
Requires-Dist: tabulate~=0.9
Requires-Dist: email-validator~=2.2.0
Provides-Extra: tests
Requires-Dist: pytest; extra == "tests"
Dynamic: license-file
